GBMProyect/GBMProyect.py
GBMProyect/__init__.py
GBMProyect-0.0.2.dist-info/LICENSE
GBMProyect-0.0.2.dist-info/METADATA
GBMProyect-0.0.2.dist-info/WHEEL
GBMProyect-0.0.2.dist-info/top_level.txt
GBMProyect-0.0.2.dist-info/RECORD
