Metadata-Version: 2.1
Name: GBMProyect
Version: 0.0.2
Summary: GBM Client Library for Python
Home-page: UNKNOWN
Author: Jason Dsouza
Author-email: raul.sosa.cortes@gmail.com
License: UNKNOWN
Keywords: python,GBM,AlgoTrading
Platform: UNKNOWN
Classifier: Programming Language :: Python :: 3
Classifier: License :: OSI Approved :: Mozilla Public License 2.0 (MPL 2.0)
Classifier: Operating System :: OS Independent
Requires-Dist: pytz
Requires-Dist: requests
